pydantic_redis/__init__.py
pydantic_redis/config.py
pydantic_redis/_shared/__init__.py
pydantic_redis/_shared/lua_scripts.py
pydantic_redis/_shared/store.py
pydantic_redis/_shared/utils.py
pydantic_redis/_shared/model/__init__.py
pydantic_redis/_shared/model/base.py
pydantic_redis/_shared/model/delete_utils.py
pydantic_redis/_shared/model/insert_utils.py
pydantic_redis/_shared/model/prop_utils.py
pydantic_redis/_shared/model/select_utils.py
pydantic_redis/asyncio/__init__.py
pydantic_redis/asyncio/model.py
pydantic_redis/asyncio/store.py
pydantic_redis/syncio/__init__.py
pydantic_redis/syncio/model.py
pydantic_redis/syncio/store.py
pydantic_redis-0.7.0.dist-info/LICENSE
pydantic_redis-0.7.0.dist-info/METADATA
pydantic_redis-0.7.0.dist-info/WHEEL
pydantic_redis-0.7.0.dist-info/top_level.txt
pydantic_redis-0.7.0.dist-info/RECORD
