Metadata-Version: 2.1
Name: pydantic-redis
Version: 0.7.0
Summary: This package provides a simple ORM for redis using pydantic-like models.
Home-page: https://github.com/sopherapps/pydantic-redis
Author: Martin Ahindura
Author-email: team.sopherapps@gmail.com
License: MIT
Classifier: License :: OSI Approved :: MIT License
Classifier: Programming Language :: Python :: 3
Classifier: Programming Language :: Python :: 3.8
License-File: LICENSE
Requires-Dist: pydantic
Requires-Dist: redis
Requires-Dist: hiredis
Requires-Dist: orjson
